stock_utilities/__init__.py
stock_utilities/correlation.py
stock_utilities/exceptions.py
stock_utilities/model.py
stock_utilities/proxy.py
stock_utilities/stock_data.py
stock_utilities-0.1.9.dist-info/WHEEL
stock_utilities-0.1.9.dist-info/METADATA
stock_utilities-0.1.9.dist-info/RECORD
