Metadata-Version: 2.1
Name: stock-utilities
Version: 0.1.9
Summary: This library is a wrapper around the finance libraries in order to give out a data model different from raw pandas and be usable in production services
Home-page: https://github.com/joxer/stock_utilities
License: GPL-3.0-only
Author: Diego Luca Candido
Requires-Python: >=3.7,<4.0
Classifier: License :: OSI Approved :: GNU General Public License v3 (GPLv3)
Classifier: Programming Language :: Python :: 3
Classifier: Programming Language :: Python :: 3.7
Classifier: Programming Language :: Python :: 3.8
Requires-Dist: praw (>=7.2.0,<8.0.0)
Requires-Dist: py_vollib (>=1.0.1,<2.0.0)
Requires-Dist: scipy (>=1.6.1,<2.0.0)
Requires-Dist: yfinance (>=0.1.55,<0.2.0)
Project-URL: Repository, https://github.com/joxer/stock_utilities
